enter/__init__.py
mw_enter-0.0.1.dist-info/WHEEL
mw_enter-0.0.1.dist-info/METADATA
mw_enter-0.0.1.dist-info/RECORD
