Metadata-Version: 2.1
Name: mw-enter
Version: 0.0.1
Summary: This is the framework for entering new worlds
Home-page: https://projects.om-office.de/frans/enter.git
Author: Frans Fürst
Author-email: frans.fuerst+gitlab@protonmail.com
Requires-Python: >=3.8,<3.11
Classifier: Programming Language :: Python :: 3
Classifier: Programming Language :: Python :: 3.8
Classifier: Programming Language :: Python :: 3.9
Classifier: Programming Language :: Python :: 3.10
Project-URL: Repository, https://projects.om-office.de/frans/enter.git
